Metadata-Version: 1.0
Name: YZ-distributions
Version: 0.1
Summary: Gaussian distributions
Home-page: UNKNOWN
Author: Yan Zhang
Author-email: yanzhang0623@gmail.com
License: UNKNOWN
Platform: UNKNOWN
